geo_ice_age/__init__.py
geo_ice_age/common.py
geo_ice_age/geo_ice_age.py
geo_ice_age-0.0.3.dist-info/LICENSE
geo_ice_age-0.0.3.dist-info/METADATA
geo_ice_age-0.0.3.dist-info/WHEEL
geo_ice_age-0.0.3.dist-info/entry_points.txt
geo_ice_age-0.0.3.dist-info/top_level.txt
geo_ice_age-0.0.3.dist-info/RECORD
