Metadata-Version: 2.1
Name: geo-ice-age
Version: 0.0.3
Summary: A python package demo for ice age analysis
Author-email: Robert Merchant <rjm288@gmail.com>
License: MIT License
Project-URL: Homepage, https://github.com/plan-9-from-outer-space/geo-ice-age
Keywords: geo-ice-age
Classifier: Intended Audience :: Developers
Classifier: License :: OSI Approved :: MIT License
Classifier: Natural Language :: English
Classifier: Programming Language :: Python :: 3.8
Classifier: Programming Language :: Python :: 3.9
Classifier: Programming Language :: Python :: 3.10
Classifier: Programming Language :: Python :: 3.11
Classifier: Programming Language :: Python :: 3.12
Requires-Python: >=3.8
License-File: LICENSE
Requires-Dist: numpy
Provides-Extra: all
Requires-Dist: geo-ice-age[extra] ; extra == 'all'
Provides-Extra: extra
Requires-Dist: pandas ; extra == 'extra'
